polywrap_logger_plugin/__init__.py
polywrap_logger_plugin/py.typed
polywrap_logger_plugin-0.1.0a1.dist-info/METADATA
polywrap_logger_plugin-0.1.0a1.dist-info/WHEEL
polywrap_logger_plugin-0.1.0a1.dist-info/RECORD
