Metadata-Version: 2.1
Name: polywrap-logger-plugin
Version: 0.1.0a1
Summary: 
Author: Niraj
Author-email: niraj@polywrap.io
Requires-Python: >=3.10,<4.0
Classifier: Programming Language :: Python :: 3
Classifier: Programming Language :: Python :: 3.10
Classifier: Programming Language :: Python :: 3.11
Requires-Dist: polywrap-core (>=0.1.0a29,<0.2.0)
Requires-Dist: polywrap-manifest (>=0.1.0a29,<0.2.0)
Requires-Dist: polywrap-msgpack (>=0.1.0a29,<0.2.0)
Requires-Dist: polywrap-plugin (==0.1.0a29)
